{"cameraMode":{"drawMode":0,"name":"Shaded","section":"Shading Mode"},"sceneLighting":false,"audioPlay":false,"sceneViewState":{"m_AlwaysRefresh":false,"showFog":true,"showSkybox":false,"showFlares":true,"showImageEffects":true,"showParticleSystems":true,"showVisualEffectGraphs":true,"m_FxEnabled":true},"in2DMode":false,"pivot":{"x":0.5,"y":1.375,"z":-4.0},"rotation":{"x":-0.21306757628917695,"y":-0.22056245803833009,"z":0.04945042356848717,"w":-0.9505501389503479},"size":10.0,"orthographic":false}